{
	"class" : {
		"aliasForPrimitive:" : "05/08/2018 06:17:04",
		"allCategories" : "05/08/2018 06:17:04",
		"compilePrimitiveLists" : "05/08/2018 06:35:24",
		"evaluate:" : "05/08/2018 06:17:04",
		"falseValue" : "05/08/2018 06:17:04",
		"falseValuePrintString" : "05/08/2018 06:17:04",
		"initialize" : "05/08/2018 06:17:04",
		"primitiveSelectors" : "05/08/2018 06:17:04",
		"primitives" : "05/08/2018 06:17:04",
		"specialForms" : "05/08/2018 06:17:04",
		"test:" : "05/08/2018 06:17:04",
		"trueValue" : "05/08/2018 06:17:04",
		"trueValuePrintString" : "05/08/2018 06:17:04" },
	"instance" : {
		"*" : "05/08/2018 06:17:04",
		"+" : "05/08/2018 06:17:04",
		"-" : "05/08/2018 06:17:04",
		"/" : "05/08/2018 06:17:04",
		"<" : "05/08/2018 06:17:04",
		"<=" : "05/08/2018 06:17:04",
		">" : "05/08/2018 06:17:04",
		">=" : "05/08/2018 06:17:04",
		"LISPand:" : "05/08/2018 06:17:04",
		"LISPor:" : "05/08/2018 06:17:04",
		"booleanP:" : "05/08/2018 06:17:04",
		"car:" : "05/08/2018 06:17:04",
		"cdr:" : "05/08/2018 06:17:04",
		"charP:" : "05/08/2018 06:17:04",
		"complexP:" : "05/08/2018 06:17:04",
		"cond:" : "05/08/2018 06:17:04",
		"cons:" : "05/08/2018 06:17:04",
		"consP:" : "05/08/2018 06:17:04",
		"constantVariables" : "Anonymous 05/08/2018 06:36",
		"constantVariables:" : "Anonymous 05/08/2018 06:36",
		"declarations" : "Anonymous 05/08/2018 06:36",
		"declarations:" : "Anonymous 05/08/2018 06:36",
		"define:" : "Anonymous 05/07/2018 05:00",
		"definePrimitiveAliases" : "05/08/2018 06:17:04",
		"enterInterpreterContextAndEval:" : "05/08/2018 06:17:04",
		"environment" : "Anonymous 05/08/2018 06:36",
		"environment:" : "Anonymous 05/08/2018 06:36",
		"eqP:" : "05/08/2018 06:17:04",
		"equalP:" : "05/08/2018 06:17:04",
		"eqvP:" : "05/08/2018 06:17:04",
		"error:" : "05/08/2018 06:17:04",
		"evalIrregularProcedure:withArguments:" : "05/08/2018 06:17:04",
		"evalList:" : "05/08/2018 06:17:04",
		"evalObject:" : "Anonymous 05/07/2018 03:51",
		"evalObject:multipleValue:" : "Anonymous 05/07/2018 03:59",
		"evalSemaphore" : "05/08/2018 06:17:04",
		"evalTailObject:" : "Anonymous 05/07/2018 05:27",
		"evaluate:" : "05/08/2018 06:17:04",
		"falseValue" : "05/08/2018 06:17:04",
		"if:" : "05/08/2018 06:17:04",
		"initialize" : "05/08/2018 06:17:04",
		"installPrimitiveAliases:" : "05/08/2018 06:17:04",
		"isProcedure:" : "Anonymous 05/08/2018 07:32",
		"lambda:" : "05/08/2018 06:17:04",
		"lambdaForm:withArgsAndBody:" : "05/08/2018 06:17:04",
		"length:" : "05/08/2018 06:17:04",
		"let:" : "05/08/2018 06:17:04",
		"letStar:" : "05/08/2018 06:17:04",
		"letrec:" : "Anonymous 05/07/2018 06:03",
		"list:" : "05/08/2018 06:17:04",
		"listP:" : "05/08/2018 06:17:04",
		"lookUpFunction:" : "Anonymous 05/08/2018 07:31",
		"not:" : "05/08/2018 06:17:04",
		"nullP:" : "05/08/2018 06:17:04",
		"progn:" : "05/08/2018 06:17:04",
		"quote:" : "05/08/2018 06:17:04",
		"set:" : "05/08/2018 06:17:04",
		"setD:" : "05/08/2018 06:17:04",
		"stringP:" : "05/08/2018 06:17:04",
		"symbolP:" : "05/08/2018 06:17:04",
		"symbolValue:ifNone:" : "Anonymous 05/08/2018 07:31",
		"symbolValuesAdd:" : "Anonymous 05/08/2018 07:07",
		"test:" : "05/08/2018 06:17:04",
		"trueValue" : "05/08/2018 06:17:04",
		"upperHead" : "Anonymous 05/08/2018 06:36",
		"upperHead:" : "Anonymous 05/08/2018 06:36",
		"upperLisp" : "Anonymous 05/08/2018 06:36",
		"upperLisp:" : "Anonymous 05/08/2018 06:36",
		"upperTail" : "Anonymous 05/08/2018 06:36",
		"upperTail:" : "Anonymous 05/08/2018 06:36" } }
