{
	"class" : {
		"actualTextStyles" : "nk 9/1/2004 11:00",
		"changeDefaultFontSizeBy:" : "ar 8/6/2009 18:36",
		"collectionFromCompressedMIMEString:" : "nice 12/27/2009 03:11",
		"decodeStyleName:" : "nk 3/25/2004 17:55",
		"default" : "Anonymous 01/30/2018 03:16",
		"defaultFamilyNames" : "nk 9/1/2004 10:59",
		"defaultFixed" : "mt 8/19/2016 15:40",
		"defaultFixedFont" : "mt 8/19/2016 15:40",
		"defaultFont" : "sw 12/6/1999 12:32",
		"fontArray:" : "Anonymous 01/30/2018 03:16",
		"fontArrayForStyle:" : "nk 7/3/2003 19:06",
		"fontPointSizesFor:" : "nk 7/3/2003 18:56",
		"fontSizeSummary" : "mt 8/2/2016 12:58",
		"fontSizeSummaryContents" : "mt 8/2/2016 12:58",
		"fontSizesFor:" : "nk 7/3/2003 18:58",
		"fontWidthsFor:" : "nk 7/3/2003 18:58",
		"importFontsFromStyleFiles" : "nice 12/27/2009 03:11",
		"initDefaultFontsAndStyle" : "Anonymous 01/30/2018 03:16",
		"initialize" : "nk 3/25/2004 17:51",
		"initializeStyleDecoder" : "nk 3/25/2004 17:53",
		"knownTextStyles" : "nice 10/21/2009 00:16",
		"knownTextStylesWithoutDefault" : "nk 9/1/2004 11:08",
		"looseFontsFromFamily:" : "nk 3/15/2004 19:37",
		"named:" : "nk 7/3/2003 19:11",
		"new" : "Anonymous 01/30/2018 03:16",
		"pixelsPerInch" : "nk 4/2/2004 11:26",
		"pixelsPerInch:" : "nk 4/2/2004 11:24",
		"pixelsToPoints:" : "nk 4/2/2004 11:23",
		"pointSizesFor:" : "nk 7/3/2003 19:11",
		"pointsToPixels:" : "nk 4/2/2004 11:22",
		"replaceFontsIn:with:" : "ar 9/5/2010 09:02",
		"replaceStyle:with:" : "nk 9/1/2004 11:03",
		"setDefault:" : "ar 1/27/2002 20:36",
		"setDefaultFixed:" : "mt 8/19/2016 15:40",
		"styleDecoder" : "bf 7/31/2009 18:21" },
	"instance" : {
		"=" : "tk 7/5/2001 22:18",
		"alignment" : "Anonymous 01/30/2018 03:16",
		"alignment:" : "ar 9/21/2000 15:17",
		"alignmentSymbol" : "ar 9/21/2000 15:16",
		"asStringOrText" : "topa 6/1/2016 20:22",
		"baseline" : "Anonymous 01/30/2018 03:16",
		"baseline:" : "Anonymous 01/30/2018 03:16",
		"centered" : "Anonymous 01/30/2018 03:16",
		"clearIndents" : "Anonymous 01/30/2018 03:16",
		"collectionFromFileNamed:" : "nice 12/27/2009 03:11",
		"compressedMIMEEncoded" : "nice 7/17/2014 23:41:04.734",
		"consistOnlyOf:" : "sw 12/8/1999 18:02",
		"consolidate" : "Anonymous 01/30/2018 03:16",
		"defaultFont" : "sw 12/6/1999 12:31",
		"defaultFontIndex" : "sw 12/6/1999 12:30",
		"defaultFontIndex:" : "sw 12/6/1999 13:50",
		"firstIndent" : "Anonymous 01/30/2018 03:16",
		"firstIndent:" : "Anonymous 01/30/2018 03:16",
		"flushFonts" : "Anonymous 01/30/2018 03:16",
		"fontArray" : "Anonymous 01/30/2018 03:16",
		"fontAt:" : "di 3/20/1999 22:31",
		"fontAt:put:" : "Anonymous 01/30/2018 03:16",
		"fontIndexOf:" : "sw 12/6/1999 13:54",
		"fontIndexOfPointSize:" : "nk 6/12/2004 16:31",
		"fontIndexOfSize:" : "di 10/11/97 09:23",
		"fontNamed:" : "Anonymous 01/30/2018 03:16",
		"fontNames" : "Anonymous 01/30/2018 03:16",
		"fontNamesAndSizes" : "tk 6/26/1998 15:03",
		"fontNamesWithPointSizes" : "ar 9/21/2000 11:53",
		"fontOfPointSize:" : "nk 6/12/2004 16:33",
		"fontOfSize:" : "di 10/11/97 09:33",
		"fonts" : "ar 12/16/2001 16:58",
		"gridForFont:withLead:" : "Anonymous 01/30/2018 03:16",
		"hash" : "ar 9/9/2003 22:04",
		"isTTCStyle" : "nk 6/25/2003 12:54",
		"justified" : "Anonymous 01/30/2018 03:16",
		"leading" : "Anonymous 01/30/2018 03:16",
		"leading:" : "Anonymous 01/30/2018 03:16",
		"leftFlush" : "Anonymous 01/30/2018 03:16",
		"leftMarginTabAt:" : "Anonymous 01/30/2018 03:16",
		"lineGrid" : "Anonymous 01/30/2018 03:16",
		"lineGrid:" : "Anonymous 01/30/2018 03:16",
		"makeArrows" : "sps 10/15/2003 17:09",
		"marginTabAt:side:" : "Anonymous 01/30/2018 03:16",
		"maxDepth" : "mt 5/9/2016 17:00",
		"newFontArray:" : "tk 8/20/96",
		"nextTabXFrom:leftMargin:rightMargin:" : "Anonymous 01/30/2018 03:16",
		"pointSizes" : "ar 12/16/2001 16:43",
		"printOn:" : "nice 10/12/2013 02:12",
		"restIndent" : "Anonymous 01/30/2018 03:16",
		"restIndent:" : "Anonymous 01/30/2018 03:16",
		"rightFlush" : "Anonymous 01/30/2018 03:16",
		"rightIndent" : "Anonymous 01/30/2018 03:16",
		"rightIndent:" : "Anonymous 01/30/2018 03:16",
		"rightMarginTabAt:" : "Anonymous 01/30/2018 03:16",
		"species" : "tk 7/5/2001 22:18",
		"storeDataOn:" : "tk 9/25/2000 10:10",
		"tabWidth" : "Anonymous 01/30/2018 03:16",
		"veryDeepCopyWith:" : "nice 1/12/2010 20:24" } }
