{
	"class" : {
		"bindingReadScanBlockFor:using:" : "",
		"bindingWriteScanBlockFor:using:" : "",
		"bytecodeSize:" : "",
		"callPrimitiveCode" : "",
		"createClosureCode" : "",
		"createClosureScanBlock" : "",
		"extensionsAt:in:into:" : "",
		"extensionsFor:in:into:" : "",
		"instVarReadScanBlockFor:using:" : "",
		"instVarWriteScanBlockFor:using:" : "",
		"interpretJumpIfCondIn:" : "",
		"interpretJumpIn:" : "",
		"interpretNextInstructionFor:in:" : "",
		"isBlockReturnAt:in:" : "",
		"isBranchIfFalseAt:in:" : "",
		"isBranchIfTrueAt:in:" : "",
		"isExtension:" : "",
		"isJumpAt:in:" : "",
		"isJustPopAt:in:" : "",
		"isNonSyntheticStoreAt:in:for:" : "",
		"isRealSendAt:in:" : "",
		"isReturnAt:in:" : "",
		"isReturnTopFromMethodAt:in:" : "",
		"isSendAt:in:" : "",
		"isStoreAt:in:" : "",
		"isStorePopAt:in:" : "",
		"isSyntheticStoreAt:in:for:" : "",
		"markerOrNilFor:" : "",
		"method:readsField:" : "",
		"method:writesField:" : "",
		"nonExtensionBytecodeAt:in:" : "",
		"nonExtensionPcAt:in:" : "",
		"pcFollowingBlockAt:in:" : "",
		"pcOfBlockCreationBytecodeForBlockStartingAt:in:" : "",
		"pcPreviousTo:in:for:" : "",
		"pushClosureBytecodeSize" : "",
		"pushNewArrayCode" : "",
		"pushNilCode" : "",
		"selectorToSendOrItselfFor:in:at:" : "",
		"stackDeltaForPrimitive:in:" : "",
		"superSendScanBlockUsing:" : "",
		"supportsClosures" : "",
		"unusedBytecode" : "" },
	"instance" : {
		"bindBlockArg:within:" : "",
		"bindBlockTemp:" : "",
		"bindBlockTemp:within:" : "",
		"bindTemp:" : "",
		"computeMethodHeaderForNumArgs:numTemps:numLits:primitive:" : "",
		"genPushNClosureTemps:" : "",
		"hasGeneratedMethod" : "",
		"if:isSpecialLiteralForPush:" : "",
		"if:isSpecialLiteralForReturn:" : "",
		"methodStreamPosition" : "",
		"nextPut:" : "",
		"noteBlockExtent:hasLocals:" : "",
		"outOfRangeError:index:range:to:" : "",
		"printSchematicTempNamesOn:blockExtents:fromIndex:" : "",
		"rootNode" : "",
		"rootNode:" : "",
		"schematicTempNamesString" : "",
		"sizeBranchPopFalse:" : "",
		"sizeBranchPopTrue:" : "",
		"sizeCallPrimitive:" : "",
		"sizeDup" : "",
		"sizeJump:" : "",
		"sizeJumpLong:" : "",
		"sizeOpcodeSelector:withArguments:" : "",
		"sizePop" : "",
		"sizePushClosureCopyNumCopiedValues:numArgs:jumpSize:" : "",
		"sizePushConsArray:" : "",
		"sizePushInstVar:" : "",
		"sizePushInstVarLong:" : "",
		"sizePushLiteral:" : "",
		"sizePushLiteralVar:" : "",
		"sizePushNClosureTemps:" : "",
		"sizePushNewArray:" : "",
		"sizePushReceiver" : "",
		"sizePushRemoteTemp:inVectorAt:" : "",
		"sizePushSpecialLiteral:" : "",
		"sizePushTemp:" : "",
		"sizePushTempLong:" : "",
		"sizePushThisContext" : "",
		"sizeReturnReceiver" : "",
		"sizeReturnSpecialLiteral:" : "",
		"sizeReturnTop" : "",
		"sizeReturnTopToCaller" : "",
		"sizeSend:numArgs:" : "",
		"sizeSendDirectedSuper:numArgs:" : "",
		"sizeSendSpecial:numArgs:" : "",
		"sizeSendSuper:numArgs:" : "",
		"sizeStoreInstVar:" : "",
		"sizeStoreInstVarLong:" : "",
		"sizeStoreLiteralVar:" : "",
		"sizeStorePopInstVar:" : "",
		"sizeStorePopInstVarLong:" : "",
		"sizeStorePopLiteralVar:" : "",
		"sizeStorePopRemoteTemp:inVectorAt:" : "",
		"sizeStorePopTemp:" : "",
		"sizeStoreRemoteTemp:inVectorAt:" : "",
		"sizeStoreTemp:" : "",
		"sizeTrapIfNotInstanceOf:" : "",
		"streamToMethod:" : "",
		"supportsFullBlocks" : "" } }
