{
	"class" : {
		 },
	"instance" : {
		"asCons" : " 05/09/2018 00:42:43",
		"asOneLispValue" : " 05/09/2018 00:42:43",
		"instVarsInclude:" : " 05/09/2018 00:42:43",
		"isCompiledProcedure" : "Anonymous 05/09/2018 02:01",
		"isComplex" : " 05/09/2018 00:42:43",
		"isConsCell" : " 05/09/2018 00:42:43",
		"isLispPrimitive" : "Anonymous 05/09/2018 01:58",
		"isLispValues" : " 05/09/2018 00:42:43",
		"isProcedure" : "Anonymous 05/09/2018 02:01",
		"pointsTo:" : " 05/09/2018 00:42:43",
		"valueForLisp:" : " 05/09/2018 00:42:43" } }
