{
	"category" : "VMMaker-Building",
	"classinstvars" : [
		 ],
	"classvars" : [
		"InterpreterTypes" ],
	"commentStamp" : "<historical>",
	"instvars" : [
		"vmMaker",
		"allPluginsList",
		"allPluginsSelection",
		"allPluginsSelectionsArray",
		"internalPluginsList",
		"internalPluginsSelection",
		"internalPluginsSelectionsArray",
		"externalPluginsList",
		"externalPluginsSelection",
		"externalPluginsSelectionsArray",
		"logger",
		"interpreterClassMorph",
		"platformPathMorph",
		"platformNameMorph",
		"generatedPathMorph",
		"configFileName" ],
	"name" : "VMMakerTool",
	"pools" : [
		 ],
	"super" : "Model",
	"type" : "normal" }
