{
	"class" : {
		"concreteClassForExtension:" : "sl 5/15/2018 13:06",
		"directoryExtensions" : "sl 5/15/2018 13:11",
		"handlesExtension:" : "sl 5/15/2018 13:18",
		"loadFrom:" : "sl 5/15/2018 13:14",
		"supportedDirectoryExtensions" : "sl 5/15/2018 13:10" },
	"instance" : {
		"<=" : "sl 5/16/2018 10:42",
		"=" : "sl 5/16/2018 10:33",
		"assureEmptyMethodFolder:" : "MS 5/17/2018 15:54",
		"category" : "MS 5/14/2018 17:04",
		"categoryMissing" : "sl 5/15/2018 12:36",
		"classInstVars" : "MS 5/14/2018 17:04",
		"classInstVarsMissing" : "sl 5/15/2018 12:37",
		"classMethods" : "sl 5/15/2018 10:21",
		"classVars" : "MS 5/14/2018 17:04",
		"classVarsMissing" : "sl 5/15/2018 12:36",
		"comment" : "sl 5/15/2018 10:22",
		"commentStamp" : "sl 5/15/2018 10:23",
		"commentStampMissing" : "sl 5/15/2018 12:37",
		"deleteExistingFiles" : "MS 5/17/2018 15:57",
		"deleteFileNamed:" : "MS 5/17/2018 16:00",
		"fileDirectory" : "MS 5/15/2018 09:53",
		"fileout" : "MS 5/17/2018 15:58",
		"fileoutComment" : "MS 5/17/2018 16:00",
		"fileoutMethods" : "MS 5/17/2018 16:03",
		"fileoutMethods:to:" : "MS 5/17/2018 16:03",
		"fileoutProperties" : "MS 5/17/2018 16:00",
		"hash" : "sl 5/16/2018 10:40",
		"instVars" : "sl 5/15/2018 10:23",
		"instVarsMissing" : "sl 5/15/2018 12:36",
		"installInto:" : "sl 5/17/2018 14:26",
		"installMethodsInto:" : "sl 5/17/2018 14:23",
		"instanceMethods" : "sl 5/15/2018 10:22",
		"loadClassComment" : "sl 5/15/2018 13:19",
		"loadClassMethods" : "sl 5/15/2018 12:53",
		"loadFromDirectory" : "sl 5/15/2018 10:09",
		"loadInstanceMethods" : "sl 5/15/2018 12:53",
		"loadProperties" : "sl 5/15/2018 10:17",
		"loadPropertiesFrom:" : "sl 5/17/2018 10:50",
		"methodsInDirectory:" : "sl 5/15/2018 14:46",
		"name" : "sl 5/16/2018 09:56",
		"nameMissing" : "sl 5/15/2018 13:20",
		"pools" : "MS 5/14/2018 17:04",
		"poolsMissing" : "sl 5/15/2018 12:36",
		"printOn:" : "sl 5/16/2018 10:49",
		"propertiesJson" : "MS 5/17/2018 15:35",
		"provisions" : "sl 5/16/2018 10:45",
		"requirements" : "sl 5/16/2018 10:19",
		"save:contents:" : "MS 5/17/2018 15:46",
		"setDirectory:" : "MS 5/15/2018 09:49",
		"shouldNotFileout" : "MS 5/17/2018 15:41",
		"superclass" : "MS 5/14/2018 17:04",
		"superclassMissing" : "sl 5/15/2018 12:37",
		"type" : "MS 5/14/2018 17:12",
		"typeMissing" : "sl 5/15/2018 12:36" } }
